{
  "@context": [
    "https://doi.org/10.5063/schema/codemeta-2.0",
    "http://schema.org"
  ],
  "@type": "SoftwareSourceCode",
  "identifier": "LEEF.analysis",
  "description": "Provides simple access functions to read data out of the sqlite RRD database. SQL queries\n  can be configured in a yaml config file and used.",
  "name": "LEEF.analysis: Access Functions, Tests and Basic Analysisof the RRD Data from the LEEF Project",
  "codeRepository": "https://github.com/LEEF-UZH/LEEF.analysis",
  "issueTracker": "https://github.com/LEEF-UZH/LEEF.analysis/issues",
  "license": "https://spdx.org/licenses/MIT",
  "version": "0.1.8",
  "programmingLanguage": {
    "@type": "ComputerLanguage",
    "name": "R",
    "url": "https://r-project.org"
  },
  "runtimePlatform": "R version 4.1.1 (2021-08-10)",
  "author": [
    {
      "@type": "Person",
      "givenName": "Rainer M.",
      "familyName": "Krug",
      "email": "Rainer.Krug@uzh.ch"
    }
  ],
  "contributor": {},
  "copyrightHolder": {},
  "funder": [
    {
      "@type": "Organization",
      "name": "SNF Project 310030_188431"
    }
  ],
  "maintainer": [
    {
      "@type": "Person",
      "givenName": "Rainer M.",
      "familyName": "Krug",
      "email": "Rainer.Krug@uzh.ch"
    }
  ],
  "softwareSuggestions": [],
  "softwareRequirements": [
    {
      "@type": "SoftwareApplication",
      "identifier": "R",
      "name": "R",
      "version": ">= 3.5.0"
    },
    {
      "@type": "SoftwareApplication",
      "identifier": "DBI",
      "name": "DBI",
      "provider": {
        "@id": "https://cran.r-project.org",
        "@type": "Organization",
        "name": "Comprehensive R Archive Network (CRAN)",
        "url": "https://cran.r-project.org"
      },
      "sameAs": "https://CRAN.R-project.org/package=DBI"
    },
    {
      "@type": "SoftwareApplication",
      "identifier": "RSQLite",
      "name": "RSQLite",
      "provider": {
        "@id": "https://cran.r-project.org",
        "@type": "Organization",
        "name": "Comprehensive R Archive Network (CRAN)",
        "url": "https://cran.r-project.org"
      },
      "sameAs": "https://CRAN.R-project.org/package=RSQLite"
    },
    {
      "@type": "SoftwareApplication",
      "identifier": "yaml",
      "name": "yaml",
      "provider": {
        "@id": "https://cran.r-project.org",
        "@type": "Organization",
        "name": "Comprehensive R Archive Network (CRAN)",
        "url": "https://cran.r-project.org"
      },
      "sameAs": "https://CRAN.R-project.org/package=yaml"
    },
    {
      "@type": "SoftwareApplication",
      "identifier": "parallel",
      "name": "parallel"
    },
    {
      "@type": "SoftwareApplication",
      "identifier": "ggplot2",
      "name": "ggplot2",
      "provider": {
        "@id": "https://cran.r-project.org",
        "@type": "Organization",
        "name": "Comprehensive R Archive Network (CRAN)",
        "url": "https://cran.r-project.org"
      },
      "sameAs": "https://CRAN.R-project.org/package=ggplot2"
    },
    {
      "@type": "SoftwareApplication",
      "identifier": "rmarkdown",
      "name": "rmarkdown",
      "provider": {
        "@id": "https://cran.r-project.org",
        "@type": "Organization",
        "name": "Comprehensive R Archive Network (CRAN)",
        "url": "https://cran.r-project.org"
      },
      "sameAs": "https://CRAN.R-project.org/package=rmarkdown"
    },
    {
      "@type": "SoftwareApplication",
      "identifier": "utils",
      "name": "utils"
    },
    {
      "@type": "SoftwareApplication",
      "identifier": "dbplyr",
      "name": "dbplyr",
      "provider": {
        "@id": "https://cran.r-project.org",
        "@type": "Organization",
        "name": "Comprehensive R Archive Network (CRAN)",
        "url": "https://cran.r-project.org"
      },
      "sameAs": "https://CRAN.R-project.org/package=dbplyr"
    },
    {
      "@type": "SoftwareApplication",
      "identifier": "dplyr",
      "name": "dplyr",
      "provider": {
        "@id": "https://cran.r-project.org",
        "@type": "Organization",
        "name": "Comprehensive R Archive Network (CRAN)",
        "url": "https://cran.r-project.org"
      },
      "sameAs": "https://CRAN.R-project.org/package=dplyr"
    }
  ],
  "fileSize": "47.672KB"
}
